LICENSE
MANIFEST.in
README.md
setup.py
django_vali/__init__.py
django_vali/settings.py
django_vali/urls.py
django_vali/wsgi.py
django_vali.egg-info/PKG-INFO
django_vali.egg-info/SOURCES.txt
django_vali.egg-info/dependency_links.txt
django_vali.egg-info/top_level.txt
vali/.DS_Store
vali/__init__.py
vali/admin.py
vali/apps.py
vali/decorator.py
vali/models.py
vali/tests.py
vali/urls.py
vali/views.py
vali/widgets.py
vali/__pycache__/__init__.cpython-36.pyc
vali/__pycache__/admin.cpython-36.pyc
vali/__pycache__/decorator.cpython-36.pyc
vali/__pycache__/models.cpython-36.pyc
vali/__pycache__/urls.cpython-36.pyc
vali/__pycache__/views.cpython-36.pyc
vali/__pycache__/widgets.cpython-36.pyc
vali/static/.DS_Store
vali/static/vali/.DS_Store
vali/static/vali/assets/.DS_Store
vali/static/vali/assets/vali.css
vali/static/vali/assets/vali.js
vali/static/vali/assets/js/.DS_Store
vali/static/vali/assets/js/bootstrap.min.js
vali/static/vali/assets/js/jquery-3.2.1.min.js
vali/static/vali/assets/js/main.js
vali/static/vali/assets/js/popper.min.js
vali/static/vali/assets/js/plugins/bootstrap-datepicker.min.js
vali/static/vali/assets/js/plugins/bootstrap-notify.min.js
vali/static/vali/assets/js/plugins/bootstrap-treeview.min.css
vali/static/vali/assets/js/plugins/bootstrap-treeview.min.js
vali/static/vali/assets/js/plugins/chart.js
vali/static/vali/assets/js/plugins/dataTables.bootstrap.min.js
vali/static/vali/assets/js/plugins/fullcalendar.min.js
vali/static/vali/assets/js/plugins/jquery-ui.custom.min.js
vali/static/vali/assets/js/plugins/jquery.dataTables.min.js
vali/static/vali/assets/js/plugins/jquery.vmap.min.js
vali/static/vali/assets/js/plugins/jquery.vmap.sampledata.js
vali/static/vali/assets/js/plugins/jquery.vmap.world.js
vali/static/vali/assets/js/plugins/moment.min.js
vali/static/vali/assets/js/plugins/pace.min.js
vali/static/vali/assets/js/plugins/select2.min.js
vali/static/vali/assets/js/plugins/sweetalert.min.js
vali/static/vali/themes/.DS_Store
vali/static/vali/themes/blue/.DS_Store
vali/static/vali/themes/blue/main.css
vali/static/vali/themes/brown/.DS_Store
vali/static/vali/themes/brown/main.css
