Metadata-Version: 2.1
Name: django-vali
Version: 0.2.0
Summary: a django admin theme using vali-admin with bootstrap4
Home-page: https://github.com/cnanyi/django-vali
Author: cnanyi
Author-email: cnanyi@gmail.com
Maintainer: cnanyi
Maintainer-email: cnanyi@gmail.com
License: MIT License
Platform: all
Classifier: Development Status :: 3 - Alpha
Classifier: Framework :: Django :: 2.0
Classifier: Intended Audience :: Developers
Classifier: License :: OSI Approved :: MIT License
Classifier: Natural Language :: English
Classifier: Programming Language :: Python :: 3.5
Classifier: Programming Language :: Python :: 3.6
